pyionoseis/__init__.py
pyionoseis/cli.py
pyionoseis/common.py
pyionoseis/pyionoseis.py
pyionoseis-0.0.1.dist-info/AUTHORS.rst
pyionoseis-0.0.1.dist-info/LICENSE
pyionoseis-0.0.1.dist-info/METADATA
pyionoseis-0.0.1.dist-info/WHEEL
pyionoseis-0.0.1.dist-info/entry_points.txt
pyionoseis-0.0.1.dist-info/top_level.txt
pyionoseis-0.0.1.dist-info/RECORD
