Metadata-Version: 2.2
Name: pyionoseis
Version: 0.0.1
Summary: A python package for modeling and anlaysis of coseismic ionospheric disturbances
Author-email: Dylan Mikesell <dylan.mikesell@gmail.com>
License: MIT License
Project-URL: Homepage, https://github.com/dylanmikesell/pyionoseis
Keywords: pyionoseis
Classifier: Intended Audience :: Developers
Classifier: License :: OSI Approved :: MIT License
Classifier: Natural Language :: English
Classifier: Programming Language :: Python :: 3.8
Classifier: Programming Language :: Python :: 3.9
Classifier: Programming Language :: Python :: 3.10
Classifier: Programming Language :: Python :: 3.11
Classifier: Programming Language :: Python :: 3.12
Requires-Python: >=3.8
License-File: LICENSE
License-File: AUTHORS.rst
Requires-Dist: numpy
Provides-Extra: all
Requires-Dist: pyionoseis[extra]; extra == "all"
Provides-Extra: extra
Requires-Dist: pandas; extra == "extra"
